{
    "label": "BOI->BCN(dt: relative(year), ms: 2, n: 7-14)",
    "airport": "BCN",
    "average": {
        "price": 675.57,
        "start": "03/30/2024 12:00:01 MDT",
        "end": "08/18/2023 12:00:02 MDT"
    },
    "min": {
        "price": 453.0,
        "date": "10/29/2023 12:00:02 MDT"
    },
    "max": {
        "price": 1041.0,
        "date": "01/11/2024 12:00:01 MDT"
    },
    "snapshot": [
        {
            "price": 753.0,
            "date": "03/30/2024 12:00:01 MDT"
        },
        {
            "price": 753.0,
            "date": "03/29/2024 12:00:01 MDT"
        },
        {
            "price": 751.0,
            "date": "03/28/2024 12:00:02 MDT"
        },
        {
            "price": 794.0,
            "date": "03/27/2024 12:00:01 MDT"
        },
        {
            "price": 781.0,
            "date": "03/26/2024 12:00:01 MDT"
        },
        {
            "price": 750.0,
            "date": "03/25/2024 12:00:01 MDT"
        },
        {
            "price": 751.0,
            "date": "03/24/2024 12:00:01 MDT"
        },
        {
            "price": 753.0,
            "date": "03/23/2024 12:00:01 MDT"
        },
        {
            "price": 769.0,
            "date": "03/22/2024 12:00:02 MDT"
        },
        {
            "price": 775.0,
            "date": "03/21/2024 12:00:02 MDT"
        },
        {
            "price": 753.0,
            "date": "03/20/2024 12:00:01 MDT"
        },
        {
            "price": 701.0,
            "date": "03/19/2024 12:00:01 MDT"
        },
        {
            "price": 755.0,
            "date": "03/18/2024 12:00:02 MDT"
        },
        {
            "price": 783.0,
            "date": "03/17/2024 12:00:01 MDT"
        },
        {
            "price": 756.0,
            "date": "03/16/2024 12:00:01 MDT"
        },
        {
            "price": 545.0,
            "date": "03/15/2024 12:00:01 MDT"
        },
        {
            "price": 543.0,
            "date": "03/14/2024 12:00:01 MDT"
        },
        {
            "price": 514.0,
            "date": "03/13/2024 12:00:02 MDT"
        },
        {
            "price": 513.0,
            "date": "03/12/2024 12:00:01 MDT"
        },
        {
            "price": 511.0,
            "date": "03/11/2024 12:00:01 MDT"
        }
    ]
}