{
    "label": "BOI->LON(dt: relative(year), ms: 4, n: 10-14)",
    "airport": "LHR",
    "average": {
        "price": 691.14,
        "start": "03/04/2024 12:00:01 MDT",
        "end": "05/19/2023 12:00:01 MDT"
    },
    "min": {
        "price": 596.0,
        "date": "10/19/2023 12:00:02 MDT"
    },
    "max": {
        "price": 792.0,
        "date": "02/27/2024 12:00:01 MDT"
    },
    "snapshot": [
        {
            "price": 631.0,
            "date": "03/04/2024 12:00:01 MDT"
        },
        {
            "price": 761.0,
            "date": "03/03/2024 12:00:01 MDT"
        },
        {
            "price": 715.0,
            "date": "03/02/2024 12:00:02 MDT"
        },
        {
            "price": 674.0,
            "date": "03/01/2024 12:00:01 MDT"
        },
        {
            "price": 671.0,
            "date": "02/29/2024 12:00:01 MDT"
        },
        {
            "price": 669.0,
            "date": "02/28/2024 12:00:02 MDT"
        },
        {
            "price": 792.0,
            "date": "02/27/2024 12:00:01 MDT"
        },
        {
            "price": 713.0,
            "date": "02/24/2024 12:00:01 MDT"
        },
        {
            "price": 715.0,
            "date": "02/23/2024 12:00:01 MDT"
        },
        {
            "price": 704.0,
            "date": "02/22/2024 12:00:01 MDT"
        },
        {
            "price": 715.0,
            "date": "02/21/2024 12:00:02 MDT"
        },
        {
            "price": 704.0,
            "date": "02/20/2024 12:00:01 MDT"
        },
        {
            "price": 759.0,
            "date": "02/19/2024 12:00:01 MDT"
        },
        {
            "price": 707.0,
            "date": "02/18/2024 12:00:02 MDT"
        },
        {
            "price": 707.0,
            "date": "02/17/2024 12:00:01 MDT"
        },
        {
            "price": 709.0,
            "date": "02/16/2024 12:00:02 MDT"
        },
        {
            "price": 710.0,
            "date": "02/15/2024 12:00:01 MDT"
        },
        {
            "price": 700.0,
            "date": "02/14/2024 12:00:02 MDT"
        },
        {
            "price": 698.0,
            "date": "02/13/2024 12:00:01 MDT"
        },
        {
            "price": 704.0,
            "date": "02/12/2024 12:00:02 MDT"
        }
    ]
}