{
    "label": "BOI->DFW(dt: relative(year), ms: 1, n: 5-8)",
    "airport": "DFW",
    "average": {
        "price": 363.68,
        "start": "03/24/2024 12:00:01 MDT",
        "end": "05/18/2023 12:00:02 MDT"
    },
    "min": {
        "price": 185.0,
        "date": "09/27/2023 12:00:01 MDT"
    },
    "max": {
        "price": 565.0,
        "date": "02/27/2024 12:00:01 MDT"
    },
    "snapshot": [
        {
            "price": 514.0,
            "date": "03/24/2024 12:00:01 MDT"
        },
        {
            "price": 519.0,
            "date": "03/23/2024 12:00:01 MDT"
        },
        {
            "price": 519.0,
            "date": "03/22/2024 12:00:02 MDT"
        },
        {
            "price": 519.0,
            "date": "03/21/2024 12:00:02 MDT"
        },
        {
            "price": 518.0,
            "date": "03/20/2024 12:00:01 MDT"
        },
        {
            "price": 500.0,
            "date": "03/19/2024 12:00:01 MDT"
        },
        {
            "price": 508.0,
            "date": "03/18/2024 12:00:02 MDT"
        },
        {
            "price": 475.0,
            "date": "03/17/2024 12:00:01 MDT"
        },
        {
            "price": 478.0,
            "date": "03/16/2024 12:00:01 MDT"
        },
        {
            "price": 468.0,
            "date": "03/15/2024 12:00:01 MDT"
        },
        {
            "price": 469.0,
            "date": "03/14/2024 12:00:01 MDT"
        },
        {
            "price": 534.0,
            "date": "03/13/2024 12:00:02 MDT"
        },
        {
            "price": 461.0,
            "date": "03/12/2024 12:00:01 MDT"
        },
        {
            "price": 459.0,
            "date": "03/11/2024 12:00:01 MDT"
        },
        {
            "price": 459.0,
            "date": "03/10/2024 12:00:03 MDT"
        },
        {
            "price": 449.0,
            "date": "03/09/2024 12:00:02 MDT"
        },
        {
            "price": 464.0,
            "date": "03/08/2024 12:00:01 MDT"
        },
        {
            "price": 518.0,
            "date": "03/07/2024 12:00:01 MDT"
        },
        {
            "price": 462.0,
            "date": "03/06/2024 12:00:01 MDT"
        },
        {
            "price": 462.0,
            "date": "03/05/2024 12:00:02 MDT"
        }
    ]
}